{
    "/assets/js/vendor.js": "/assets/js/vendor.js?id=24ca571bb7a7c34bddd0",
    "/assets/js/vendor.js.map": "/assets/js/vendor.js.map?id=ca504f485ea1b0c185f1",
    "/assets/js/app.js": "/assets/js/app.js?id=93d73187425fadd1d6dd",
    "/assets/css/app.css": "/assets/css/app.css?id=751526e3e555e21a2b5e",
    "/assets/js/app.js.map": "/assets/js/app.js.map?id=34138784afe66b5a6c4d",
    "/assets/css/app.css.map": "/assets/css/app.css.map?id=22d8f98de1a9a13a25d0",
    "/assets/js/manifest.js": "/assets/js/manifest.js?id=bb58468fac8d92ddbd39",
    "/assets/js/manifest.js.map": "/assets/js/manifest.js.map?id=d0847af1ec4c9728ae57"
}