{
    "/assets/js/app.js": "/assets/js/app.js?id=d8adc1923806b8cf19df",
    "/assets/css/app.css": "/assets/css/app.css?id=328f678d8d0ef5252767",
    "/assets/js/app.js.map": "/assets/js/app.js.map?id=45319e3c06c1e3507153",
    "/assets/css/app.css.map": "/assets/css/app.css.map?id=8c10318f4004f2174227",
    "/assets/js/vendor.js": "/assets/js/vendor.js?id=a532a48ecdacaf36d14e",
    "/assets/js/vendor.js.map": "/assets/js/vendor.js.map?id=e649ff994a7bd3c06c35",
    "/assets/js/manifest.js": "/assets/js/manifest.js?id=bb58468fac8d92ddbd39",
    "/assets/js/manifest.js.map": "/assets/js/manifest.js.map?id=93393204b11b14d4c3e5"
}
